{
  "$schema": "https://developer.microsoft.com/json-schemas/spfx-build/package-solution.schema.json",
  "solution": {
    "name": "my-own-css-client-side-solution",
    "id": "9ea2981c-af12-41ef-ac17-6fe677f28bcc",
    "version": "1.0.0.0",
    "includeClientSideAssets": true,
    "isDomainIsolated": false,
    "developer": {
      "name": "",
      "websiteUrl": "",
      "privacyUrl": "",
      "termsOfUseUrl": "",
      "mpnId": ""
    },
    "features": [
      {
        "title": "Application Extension - Deployment of custom action.",
        "description": "Deploys a custom action with ClientSideComponentId association",
        "id": "1bb3a4bc-0dee-44f3-9cb4-1da7f7cc8a0c",
        "version": "1.0.0.0",
        "assets": {
          "elementManifests": [
            "elements.xml",
            "ClientSideInstance.xml"
          ]
        }
      }
    ]
  },
  "paths": {
    "zippedPackage": "solution/my-own-css.sppkg"
  }
}
